edn_conf/__init__.py
edn_conf/core.py
edn_conf/eval.py
edn_conf/tags.edn
edn_conf/tags.py
edn_configs-0.0.2.dist-info/LICENSE
edn_configs-0.0.2.dist-info/METADATA
edn_configs-0.0.2.dist-info/WHEEL
edn_configs-0.0.2.dist-info/top_level.txt
edn_configs-0.0.2.dist-info/RECORD
