Metadata-Version: 2.1
Name: edn-configs
Version: 0.0.2
Summary: Edn enhanced config parser
Author-email: Massimiliano Falzari <m.falzari@student.rug.nl>
Project-URL: Homepage, https://github.com/vimmoos/edn_conf
Classifier: Programming Language :: Python :: 3
Classifier: License :: OSI Approved :: GNU Lesser General Public License v3 (LGPLv3)
Classifier: Operating System :: POSIX :: Linux
Requires-Python: >=3.7
License-File: LICENSE
Requires-Dist: edn-format
